sustechthesis/__init__.py
sustechthesis/__main__.py
sustechthesis/config.py
sustechthesis/utils.py
sustechthesis/commands/__init__.py
sustechthesis/commands/build.py
sustechthesis/commands/clean.py
sustechthesis/commands/doc.py
sustechthesis/commands/issue.py
sustechthesis/commands/new.py
sustechthesis/commands/view.py
sustechthesis-0.1.dist-info/LICENSE
sustechthesis-0.1.dist-info/METADATA
sustechthesis-0.1.dist-info/WHEEL
sustechthesis-0.1.dist-info/entry_points.txt
sustechthesis-0.1.dist-info/top_level.txt
sustechthesis-0.1.dist-info/RECORD
