Metadata-Version: 2.1
Name: sustechthesis
Version: 0.1
Summary: SUSTech Thesis
Home-page: https://github.com/Iydon/pypi
Author: Iydon Liang
Author-email: 11711217@mail.sustech.edu.cn
License: MIT License
Platform: UNKNOWN
Classifier: Programming Language :: Python :: 3
Classifier: Environment :: Console
Classifier: License :: OSI Approved :: MIT License
Classifier: Operating System :: OS Independent
Requires-Dist: click (>=3.3)
